{
    "success": true,
    "data": [
        {
            "ID": 1,
            "ProductID": 1,
            "SKU": "SKU-12345",
            "Name": "Продукт 1",
            "Power": "100W",
            "LuminousFlux": "12000lm",
            "Efficiency": "120lm/W",
            "ColorTemp": "4000K",
            "CRI": "Ra>80",
            "ProtectionClass": "IP65",
            "ClimateExecution": "Умеренный",
            "EmergencyPowerUnit": "Есть",
            "BeamAngle": "120°",
            "KCC": "KCC-12345",
            "Warranty": "2 года",
            "RetailPrice": 150.00,
            "WholesalePrice": 120.00,
            "DealerPrice1": 110.00,
            "DealerPrice2": 105.00,
            "DealerPrice3": 100.00,
            "full-path": "full-path",
            "CreatedAt": "2023-01-01T00:00:00Z",
            "UpdatedAt": "2023-01-02T00:00:00Z"
        },
        {
            "ID": 2,
            "ProductID": 2,
            "SKU": "SKU-12346",
            "Name": "Продукт 2",
            "Power": "150W",
            "LuminousFlux": "15000lm",
            "Efficiency": "130lm/W",
            "ColorTemp": "4500K",
            "CRI": "Ra>85",
            "ProtectionClass": "IP67",
            "ClimateExecution": "Умеренный",
            "EmergencyPowerUnit": "Есть",
            "BeamAngle": "150°",
            "KCC": "KCC-12346",
            "Warranty": "3 года",
            "RetailPrice": 180.00,
            "WholesalePrice": 140.00,
            "DealerPrice1": 120.00,
            "DealerPrice2": 115.00,
            "DealerPrice3": 110.00,
            "full-path": "full-path",
            "CreatedAt": "2023-01-03T00:00:00Z",
            "UpdatedAt": "2023-01-04T00:00:00Z"
        }
    ]
}